{"id": "D6Aw3ZnqQrY", "title": "Roy Orbison - Only the Lonely (Black & White Night 30)", "formats": [{"asr": 48000, "filesize": 1006145, "format_id": "249", "format_note": "tiny", "fps": null, "height": null, "quality": 0, "tbr": 52.138, "url": "https://rr4---sn-0opoxu-ihv6.googlevideo.com/videoplayback?expire=1670740054&ei=9iOVY_j3KI2Ekgbqv4OoBA&ip=189.173.225.87&id=o-ADn5HJX_4ula4wHmV_FRxM8Tw5xvZmIBC4r7Sp-pgjAL&itag=249&source=youtube&requiressl=yes&mh=oY&mm=31%2C29&mn=sn-0opoxu-ihv6%2Csn-q4fzen7l&ms=au%2Crdu&mv=m&mvi=4&pl=24&gcr=mx&initcwndbps=793750&vprv=1&mime=audio%2Fwebm&ns=FnthCqCD_zH0CFDuXEsFohEJ&gir=yes&clen=1006145&dur=154.381&lmt=1604863508855557&mt=1670718069&fvip=1&keepalive=yes&fexp=24001373%2C24007246&c=WEB&txp=5432434&n=UQts7oCbq-bc9e_WB&sparams=expire%2Cei%2Cip%2Cid%2Citag%2Csource%2Crequiressl%2Cgcr%2Cvprv%2Cmime%2Cns%2Cgir%2Cclen%2Cdur%2Clmt&lsparams=mh%2Cmm%2Cmn%2Cms%2Cmv%2Cmvi%2Cpl%2Cinitcwndbps&lsig=AG3C_xAwRAIgNvVZ8mAuUtQcN2sIeSzleyrbPzya-Ou-7_P3x7RMPAwCIBx0xPYImyl0N98VVZbCUYD53d8HBaz0w3UJL61-sWMX&sig=AOq0QJ8wRAIgck9XJIkxb48-mim7s7c2b8NxbnwI8BBXwCkbGUgX7n0CIGXGu_k3LAflOtzQjMkEuXwWdKtiSxFaCpJf--oywZLi", "width": null, "ext": "webm", "vcodec": "none", "acodec": "opus", "abr": 52.138, "downloader_options": {"http_chunk_size": 10485760}, "container": "webm_dash", "format": "249 - audio only (tiny)", "protocol": "https", "http_headers": {"User-Agent": "Mozilla/5.0 (Windows NT 10.0; Win64; x64) AppleWebKit/537.36 (KHTML, like Gecko) Chrome/73.0.3683.60 Safari/537.36", "Accept-Charset": "ISO-8859-1,utf-8;q=0.7,*;q=0.7", "Accept": "text/html,application/xhtml+xml,application/xml;q=0.9,*/*;q=0.8", "Accept-Encoding": "gzip, deflate", "Accept-Language": "en-us,en;q=0.5"}}, {"asr": 48000, "filesize": 1334221, "format_id": "250", "format_note": "tiny", "fps": null, "height": null, "quality": 0, "tbr": 69.139, "url": "https://rr4---sn-0opoxu-ihv6.googlevideo.com/videoplayback?expire=1670740054&ei=9iOVY_j3KI2Ekgbqv4OoBA&ip=189.173.225.87&id=o-ADn5HJX_4ula4wHmV_FRxM8Tw5xvZmIBC4r7Sp-pgjAL&itag=250&source=youtube&requiressl=yes&mh=oY&mm=31%2C29&mn=sn-0opoxu-ihv6%2Csn-q4fzen7l&ms=au%2Crdu&mv=m&mvi=4&pl=24&gcr=mx&initcwndbps=793750&vprv=1&mime=audio%2Fwebm&ns=FnthCqCD_zH0CFDuXEsFohEJ&gir=yes&clen=1334221&dur=154.381&lmt=1604863509762654&mt=1670718069&fvip=1&keepalive=yes&fexp=24001373%2C24007246&c=WEB&txp=5432434&n=UQts7oCbq-bc9e_WB&sparams=expire%2Cei%2Cip%2Cid%2Citag%2Csource%2Crequiressl%2Cgcr%2Cvprv%2Cmime%2Cns%2Cgir%2Cclen%2Cdur%2Clmt&lsparams=mh%2Cmm%2Cmn%2Cms%2Cmv%2Cmvi%2Cpl%2Cinitcwndbps&lsig=AG3C_xAwRQIgHShhBqY_uVaxYfnY0lhs7SUZvnROKSStVz63HvJ0snMCIQD_2cxXD-WuEDX8EkPjRx41XcJAA0aG9tBPspTXYDGqkw%3D%3D&sig=AOq0QJ8wRQIhAJ3g8c-laLKXuIVzQPEA4UUs7nAnWVdhjzAH031PL6zAAiAkwS1bdxvHHTh-seVfUyE_mYXmz0pm2cVAMhFah50heA==", "width": null, "ext": "webm", "vcodec": "none", "acodec": "opus", "abr": 69.139, "downloader_options": {"http_chunk_size": 10485760}, "container": "webm_dash", "format": "250 - audio only (tiny)", "protocol": "https", "http_headers": {"User-Agent": "Mozilla/5.0 (Windows NT 10.0; Win64; x64) AppleWebKit/537.36 (KHTML, like Gecko) Chrome/73.0.3683.60 Safari/537.36", "Accept-Charset": "ISO-8859-1,utf-8;q=0.7,*;q=0.7", "Accept": "text/html,application/xhtml+xml,application/xml;q=0.9,*/*;q=0.8", "Accept-Encoding": "gzip, deflate", "Accept-Language": "en-us,en;q=0.5"}}, {"asr": 44100, "filesize": 2499723, "format_id": "140", "format_note": "tiny", "fps": null, "height": null, "quality": 0, "tbr": 129.509, "url": "https://rr4---sn-0opoxu-ihv6.googlevideo.com/videoplayback?expire=1670740054&ei=9iOVY_j3KI2Ekgbqv4OoBA&ip=189.173.225.87&id=o-ADn5HJX_4ula4wHmV_FRxM8Tw5xvZmIBC4r7Sp-pgjAL&itag=140&source=youtube&requiressl=yes&mh=oY&mm=31%2C29&mn=sn-0opoxu-ihv6%2Csn-q4fzen7l&ms=au%2Crdu&mv=m&mvi=4&pl=24&gcr=mx&initcwndbps=793750&vprv=1&mime=audio%2Fmp4&ns=FnthCqCD_zH0CFDuXEsFohEJ&gir=yes&clen=2499723&dur=154.412&lmt=1604863511603353&mt=1670718069&fvip=1&keepalive=yes&fexp=24001373%2C24007246&c=WEB&txp=5432434&n=UQts7oCbq-bc9e_WB&sparams=expire%2Cei%2Cip%2Cid%2Citag%2Csource%2Crequiressl%2Cgcr%2Cvprv%2Cmime%2Cns%2Cgir%2Cclen%2Cdur%2Clmt&lsparams=mh%2Cmm%2Cmn%2Cms%2Cmv%2Cmvi%2Cpl%2Cinitcwndbps&lsig=AG3C_xAwRQIgbHH1LkVXGpKiYg8CX0zLr9F0lfFdDLVUZt3fD72u7KkCIQDFuLS2dIEtRA-FGdy31npoOB0nydT6sXFMu_ycDmihOw%3D%3D&sig=AOq0QJ8wRAIgHQ6k-lKokfYwpnpxwXy70sTav-LWv_Fb63H29VX-oAUCIG_DjdXtbrVKKeNnN4RmkYpg06-iypg2p8HE4NDLkq2D", "width": null, "ext": "m4a", "vcodec": "none", "acodec": "mp4a.40.2", "abr": 129.509, "downloader_options": {"http_chunk_size": 10485760}, "container": "m4a_dash", "format": "140 - audio only (tiny)", "protocol": "https", "http_headers": {"User-Agent": "Mozilla/5.0 (Windows NT 10.0; Win64; x64) AppleWebKit/537.36 (KHTML, like Gecko) Chrome/73.0.3683.60 Safari/537.36", "Accept-Charset": "ISO-8859-1,utf-8;q=0.7,*;q=0.7", "Accept": "text/html,application/xhtml+xml,application/xml;q=0.9,*/*;q=0.8", "Accept-Encoding": "gzip, deflate", "Accept-Language": "en-us,en;q=0.5"}}, {"asr": 48000, "filesize": 2622106, "format_id": "251", "format_note": "tiny", "fps": null, "height": null, "quality": 0, "tbr": 135.877, "url": "https://rr4---sn-0opoxu-ihv6.googlevideo.com/videoplayback?expire=1670740054&ei=9iOVY_j3KI2Ekgbqv4OoBA&ip=189.173.225.87&id=o-ADn5HJX_4ula4wHmV_FRxM8Tw5xvZmIBC4r7Sp-pgjAL&itag=251&source=youtube&requiressl=yes&mh=oY&mm=31%2C29&mn=sn-0opoxu-ihv6%2Csn-q4fzen7l&ms=au%2Crdu&mv=m&mvi=4&pl=24&gcr=mx&initcwndbps=793750&vprv=1&mime=audio%2Fwebm&ns=FnthCqCD_zH0CFDuXEsFohEJ&gir=yes&clen=2622106&dur=154.381&lmt=1604863512065992&mt=1670718069&fvip=1&keepalive=yes&fexp=24001373%2C24007246&c=WEB&txp=5432434&n=UQts7oCbq-bc9e_WB&sparams=expire%2Cei%2Cip%2Cid%2Citag%2Csource%2Crequiressl%2Cgcr%2Cvprv%2Cmime%2Cns%2Cgir%2Cclen%2Cdur%2Clmt&lsparams=mh%2Cmm%2Cmn%2Cms%2Cmv%2Cmvi%2Cpl%2Cinitcwndbps&lsig=AG3C_xAwRgIhAO2PRA6Jbeesnn_R5KQ9VNqxzu9N_eOhkrA0qF4wFvfDAiEAo8_KfCyddzIdv8z0Mgb6LrKN4uIOMf8hicOWSqa-AAY%3D&sig=AOq0QJ8wRQIgJjVrrLGIr4GSRi299lmp83M7qdOiRB5QzD-nBu_0XRMCIQDIoA9lxBG0tPFB4v3RcURZgev7aM8Dnsda8-VLLZMIqg==", "width": null, "ext": "webm", "vcodec": "none", "acodec": "opus", "abr": 135.877, "downloader_options": {"http_chunk_size": 10485760}, "container": "webm_dash", "format": "251 - audio only (tiny)", "protocol": "https", "http_headers": {"User-Agent": "Mozilla/5.0 (Windows NT 10.0; Win64; x64) AppleWebKit/537.36 (KHTML, like Gecko) Chrome/73.0.3683.60 Safari/537.36", "Accept-Charset": "ISO-8859-1,utf-8;q=0.7,*;q=0.7", "Accept": "text/html,application/xhtml+xml,application/xml;q=0.9,*/*;q=0.8", "Accept-Encoding": "gzip, deflate", "Accept-Language": "en-us,en;q=0.5"}}, {"asr": null, "filesize": 956150, "format_id": "160", "format_note": "144p", "fps": 24, "height": 144, "quality": 0, "tbr": 49.553, "url": "https://rr4---sn-0opoxu-ihv6.googlevideo.com/videoplayback?expire=1670740054&ei=9iOVY_j3KI2Ekgbqv4OoBA&ip=189.173.225.87&id=o-ADn5HJX_4ula4wHmV_FRxM8Tw5xvZmIBC4r7Sp-pgjAL&itag=160&aitags=133%2C134%2C135%2C136%2C137%2C160%2C242%2C243%2C244%2C247%2C248%2C278%2C394%2C395%2C396%2C397%2C398%2C399&source=youtube&requiressl=yes&mh=oY&mm=31%2C29&mn=sn-0opoxu-ihv6%2Csn-q4fzen7l&ms=au%2Crdu&mv=m&mvi=4&pl=24&gcr=mx&initcwndbps=793750&vprv=1&mime=video%2Fmp4&ns=FnthCqCD_zH0CFDuXEsFohEJ&gir=yes&clen=956150&dur=154.362&lmt=1604864106761698&mt=1670718069&fvip=1&keepalive=yes&fexp=24001373%2C24007246&c=WEB&txp=5432434&n=UQts7oCbq-bc9e_WB&sparams=expire%2Cei%2Cip%2Cid%2Caitags%2Csource%2Crequiressl%2Cgcr%2Cvprv%2Cmime%2Cns%2Cgir%2Cclen%2Cdur%2Clmt&lsparams=mh%2Cmm%2Cmn%2Cms%2Cmv%2Cmvi%2Cpl%2Cinitcwndbps&lsig=AG3C_xAwRgIhAPw8g-xaxhfL5lrzzdqEsB7_2ckXN3JiLr3TtNHbDDCtAiEAyj6fWXXJdngFYb-vJNHmY-GYRDIkynlaRRMb3aFIyPU%3D&sig=AOq0QJ8wRQIgQT5nRlmoSW__sWCVU6ZJ4Edo4QkrDZuIvX-Amm7K5eACIQDPH6Snrnauz7DW15v-Mnowko4BZ45TVDwv5xHEfkgHXg==", "width": 256, "ext": "mp4", "vcodec": "avc1.4d400c", "acodec": "none", "vbr": 49.553, "downloader_options": {"http_chunk_size": 10485760}, "container": "mp4_dash", "format": "160 - 256x144 (144p)", "protocol": "https", "http_headers": {"User-Agent": "Mozilla/5.0 (Windows NT 10.0; Win64; x64) AppleWebKit/537.36 (KHTML, like Gecko) Chrome/73.0.3683.60 Safari/537.36", "Accept-Charset": "ISO-8859-1,utf-8;q=0.7,*;q=0.7", "Accept": "text/html,application/xhtml+xml,application/xml;q=0.9,*/*;q=0.8", "Accept-Encoding": "gzip, deflate", "Accept-Language": "en-us,en;q=0.5"}}, {"asr": null, "filesize": 1582566, "format_id": "278", "format_note": "144p", "fps": 24, "height": 144, "quality": 0, "tbr": 82.018, "url": "https://rr4---sn-0opoxu-ihv6.googlevideo.com/videoplayback?expire=1670740054&ei=9iOVY_j3KI2Ekgbqv4OoBA&ip=189.173.225.87&id=o-ADn5HJX_4ula4wHmV_FRxM8Tw5xvZmIBC4r7Sp-pgjAL&itag=278&aitags=133%2C134%2C135%2C136%2C137%2C160%2C242%2C243%2C244%2C247%2C248%2C278%2C394%2C395%2C396%2C397%2C398%2C399&source=youtube&requiressl=yes&mh=oY&mm=31%2C29&mn=sn-0opoxu-ihv6%2Csn-q4fzen7l&ms=au%2Crdu&mv=m&mvi=4&pl=24&gcr=mx&initcwndbps=793750&vprv=1&mime=video%2Fwebm&ns=FnthCqCD_zH0CFDuXEsFohEJ&gir=yes&clen=1582566&dur=154.362&lmt=1604864120125494&mt=1670718069&fvip=1&keepalive=yes&fexp=24001373%2C24007246&c=WEB&txp=5432434&n=UQts7oCbq-bc9e_WB&sparams=expire%2Cei%2Cip%2Cid%2Caitags%2Csource%2Crequiressl%2Cgcr%2Cvprv%2Cmime%2Cns%2Cgir%2Cclen%2Cdur%2Clmt&lsparams=mh%2Cmm%2Cmn%2Cms%2Cmv%2Cmvi%2Cpl%2Cinitcwndbps&lsig=AG3C_xAwRgIhAKimy8Pov2DQt31h7uY8uiarw2bEQnxhTIfNY5p6n_isAiEA5_AQouhJ4wD--0mR-WZ2D9QJCj79bkeTRk4ADxamZH0%3D&sig=AOq0QJ8wRQIhAKdGaUKZ3HFlFQlnvRweqQTEzODeRtjNaiJNxY7Rnf1vAiAZQB4eqn3ceXrNy7R159aJo-fScHLyaCoKZBzlF3zndw==", "width": 256, "ext": "webm", "vcodec": "vp9", "acodec": "none", "vbr": 82.018, "downloader_options": {"http_chunk_size": 10485760}, "container": "webm_dash", "format": "278 - 256x144 (144p)", "protocol": "https", "http_headers": {"User-Agent": "Mozilla/5.0 (Windows NT 10.0; Win64; x64) AppleWebKit/537.36 (KHTML, like Gecko) Chrome/73.0.3683.60 Safari/537.36", "Accept-Charset": "ISO-8859-1,utf-8;q=0.7,*;q=0.7", "Accept": "text/html,application/xhtml+xml,application/xml;q=0.9,*/*;q=0.8", "Accept-Encoding": "gzip, deflate", "Accept-Language": "en-us,en;q=0.5"}}, {"asr": null, "filesize": 1848570, "format_id": "394", "format_note": "144p", "fps": 24, "height": 144, "quality": 0, "tbr": 95.804, "url": "https://rr4---sn-0opoxu-ihv6.googlevideo.com/videoplayback?expire=1670740054&ei=9iOVY_j3KI2Ekgbqv4OoBA&ip=189.173.225.87&id=o-ADn5HJX_4ula4wHmV_FRxM8Tw5xvZmIBC4r7Sp-pgjAL&itag=394&aitags=133%2C134%2C135%2C136%2C137%2C160%2C242%2C243%2C244%2C247%2C248%2C278%2C394%2C395%2C396%2C397%2C398%2C399&source=youtube&requiressl=yes&mh=oY&mm=31%2C29&mn=sn-0opoxu-ihv6%2Csn-q4fzen7l&ms=au%2Crdu&mv=m&mvi=4&pl=24&gcr=mx&initcwndbps=793750&vprv=1&mime=video%2Fmp4&ns=FnthCqCD_zH0CFDuXEsFohEJ&gir=yes&clen=1848570&dur=154.362&lmt=1622261456435305&mt=1670718069&fvip=1&keepalive=yes&fexp=24001373%2C24007246&c=WEB&txp=5436432&n=UQts7oCbq-bc9e_WB&sparams=expire%2Cei%2Cip%2Cid%2Caitags%2Csource%2Crequiressl%2Cgcr%2Cvprv%2Cmime%2Cns%2Cgir%2Cclen%2Cdur%2Clmt&lsparams=mh%2Cmm%2Cmn%2Cms%2Cmv%2Cmvi%2Cpl%2Cinitcwndbps&lsig=AG3C_xAwRQIgLRUEdIj3N7sPw__siOCT8mbRkioWK9LDK2atRe4br9YCIQCKus80bl95I1fjC2kKhFKANheBNBXHZqeZg5tjf4jZFw%3D%3D&sig=AOq0QJ8wRQIgNRcVN0RPyqGu49IsNCveT-CWyBZXArclNBNL5nFJ0cgCIQCFOOcDI4tS4sVhzVUa4X-ePUlKYCdG7T17Gr0aKmh0bg==", "width": 256, "ext": "mp4", "vcodec": "av01.0.00M.08", "acodec": "none", "vbr": 95.804, "downloader_options": {"http_chunk_size": 10485760}, "container": "mp4_dash", "format": "394 - 256x144 (144p)", "protocol": "https", "http_headers": {"User-Agent": "Mozilla/5.0 (Windows NT 10.0; Win64; x64) AppleWebKit/537.36 (KHTML, like Gecko) Chrome/73.0.3683.60 Safari/537.36", "Accept-Charset": "ISO-8859-1,utf-8;q=0.7,*;q=0.7", "Accept": "text/html,application/xhtml+xml,application/xml;q=0.9,*/*;q=0.8", "Accept-Encoding": "gzip, deflate", "Accept-Language": "en-us,en;q=0.5"}}, {"asr": null, "filesize": 2006764, "format_id": "133", "format_note": "240p", "fps": 24, "height": 240, "quality": 1, "tbr": 104.003, "url": "https://rr4---sn-0opoxu-ihv6.googlevideo.com/videoplayback?expire=1670740054&ei=9iOVY_j3KI2Ekgbqv4OoBA&ip=189.173.225.87&id=o-ADn5HJX_4ula4wHmV_FRxM8Tw5xvZmIBC4r7Sp-pgjAL&itag=133&aitags=133%2C134%2C135%2C136%2C137%2C160%2C242%2C243%2C244%2C247%2C248%2C278%2C394%2C395%2C396%2C397%2C398%2C399&source=youtube&requiressl=yes&mh=oY&mm=31%2C29&mn=sn-0opoxu-ihv6%2Csn-q4fzen7l&ms=au%2Crdu&mv=m&mvi=4&pl=24&gcr=mx&initcwndbps=793750&vprv=1&mime=video%2Fmp4&ns=FnthCqCD_zH0CFDuXEsFohEJ&gir=yes&clen=2006764&dur=154.362&lmt=1604864086225267&mt=1670718069&fvip=1&keepalive=yes&fexp=24001373%2C24007246&c=WEB&txp=5432434&n=UQts7oCbq-bc9e_WB&sparams=expire%2Cei%2Cip%2Cid%2Caitags%2Csource%2Crequiressl%2Cgcr%2Cvprv%2Cmime%2Cns%2Cgir%2Cclen%2Cdur%2Clmt&lsparams=mh%2Cmm%2Cmn%2Cms%2Cmv%2Cmvi%2Cpl%2Cinitcwndbps&lsig=AG3C_xAwRgIhAPO9gg4Mr-06NYjgNOyWPZcadMgHSTrRZOPmGaWMfkpuAiEA_yKzZjKIW7ffPonBo6kzukU78hTQn8q996gv7nuvxSk%3D&sig=AOq0QJ8wRQIhAP9BwwY5naOWC3aJzMdKkrYmHDefkN-c2tVNHQoKIT83AiBQu3xxdzh4lhXhio7-X-WGm9NUsdwvqUfE54AacFfvKg==", "width": 426, "ext": "mp4", "vcodec": "avc1.4d4015", "acodec": "none", "vbr": 104.003, "downloader_options": {"http_chunk_size": 10485760}, "container": "mp4_dash", "format": "133 - 426x240 (240p)", "protocol": "https", "http_headers": {"User-Agent": "Mozilla/5.0 (Windows NT 10.0; Win64; x64) AppleWebKit/537.36 (KHTML, like Gecko) Chrome/73.0.3683.60 Safari/537.36", "Accept-Charset": "ISO-8859-1,utf-8;q=0.7,*;q=0.7", "Accept": "text/html,application/xhtml+xml,application/xml;q=0.9,*/*;q=0.8", "Accept-Encoding": "gzip, deflate", "Accept-Language": "en-us,en;q=0.5"}}, {"asr": null, "filesize": 2669961, "format_id": "242", "format_note": "240p", "fps": 24, "height": 240, "quality": 1, "tbr": 138.374, "url": "https://rr4---sn-0opoxu-ihv6.googlevideo.com/videoplayback?expire=1670740054&ei=9iOVY_j3KI2Ekgbqv4OoBA&ip=189.173.225.87&id=o-ADn5HJX_4ula4wHmV_FRxM8Tw5xvZmIBC4r7Sp-pgjAL&itag=242&aitags=133%2C134%2C135%2C136%2C137%2C160%2C242%2C243%2C244%2C247%2C248%2C278%2C394%2C395%2C396%2C397%2C398%2C399&source=youtube&requiressl=yes&mh=oY&mm=31%2C29&mn=sn-0opoxu-ihv6%2Csn-q4fzen7l&ms=au%2Crdu&mv=m&mvi=4&pl=24&gcr=mx&initcwndbps=793750&vprv=1&mime=video%2Fwebm&ns=FnthCqCD_zH0CFDuXEsFohEJ&gir=yes&clen=2669961&dur=154.362&lmt=1604864121220069&mt=1670718069&fvip=1&keepalive=yes&fexp=24001373%2C24007246&c=WEB&txp=5432434&n=UQts7oCbq-bc9e_WB&sparams=expire%2Cei%2Cip%2Cid%2Caitags%2Csource%2Crequiressl%2Cgcr%2Cvprv%2Cmime%2Cns%2Cgir%2Cclen%2Cdur%2Clmt&lsparams=mh%2Cmm%2Cmn%2Cms%2Cmv%2Cmvi%2Cpl%2Cinitcwndbps&lsig=AG3C_xAwRAIgJ8lxH8q7wNh241_N94OpMwj04otVryOOxzpH-nVbSvsCIEhwU4NuyTRbVsxwc14pgMDlK3CK0nybPFxVAb4B1Cad&sig=AOq0QJ8wRQIhAJTeikyMCcl6tqTIDhH08z4hICluvXmbhtg4Sm9eZ-ysAiBi3FanRjS59FeQ3LBvruybI2Z6-7gxbKUp9oV8XR8_yw==", "width": 426, "ext": "webm", "vcodec": "vp9", "acodec": "none", "vbr": 138.374, "downloader_options": {"http_chunk_size": 10485760}, "container": "webm_dash", "format": "242 - 426x240 (240p)", "protocol": "https", "http_headers": {"User-Agent": "Mozilla/5.0 (Windows NT 10.0; Win64; x64) AppleWebKit/537.36 (KHTML, like Gecko) Chrome/73.0.3683.60 Safari/537.36", "Accept-Charset": "ISO-8859-1,utf-8;q=0.7,*;q=0.7", "Accept": "text/html,application/xhtml+xml,application/xml;q=0.9,*/*;q=0.8", "Accept-Encoding": "gzip, deflate", "Accept-Language": "en-us,en;q=0.5"}}, {"asr": null, "filesize": 3916030, "format_id": "395", "format_note": "240p", "fps": 24, "height": 240, "quality": 1, "tbr": 202.953, "url": "https://rr4---sn-0opoxu-ihv6.googlevideo.com/videoplayback?expire=1670740054&ei=9iOVY_j3KI2Ekgbqv4OoBA&ip=189.173.225.87&id=o-ADn5HJX_4ula4wHmV_FRxM8Tw5xvZmIBC4r7Sp-pgjAL&itag=395&aitags=133%2C134%2C135%2C136%2C137%2C160%2C242%2C243%2C244%2C247%2C248%2C278%2C394%2C395%2C396%2C397%2C398%2C399&source=youtube&requiressl=yes&mh=oY&mm=31%2C29&mn=sn-0opoxu-ihv6%2Csn-q4fzen7l&ms=au%2Crdu&mv=m&mvi=4&pl=24&gcr=mx&initcwndbps=793750&vprv=1&mime=video%2Fmp4&ns=FnthCqCD_zH0CFDuXEsFohEJ&gir=yes&clen=3916030&dur=154.362&lmt=1622261456029308&mt=1670718069&fvip=1&keepalive=yes&fexp=24001373%2C24007246&c=WEB&txp=5436432&n=UQts7oCbq-bc9e_WB&sparams=expire%2Cei%2Cip%2Cid%2Caitags%2Csource%2Crequiressl%2Cgcr%2Cvprv%2Cmime%2Cns%2Cgir%2Cclen%2Cdur%2Clmt&lsparams=mh%2Cmm%2Cmn%2Cms%2Cmv%2Cmvi%2Cpl%2Cinitcwndbps&lsig=AG3C_xAwRQIgFret1_sicgSo-q93sj6LnddATsOO9Gh5ZMdY7xhsmjsCIQDVSWKvxFc72OcXUM3Awm6bgrX5iSsCGj2SCVg4v-2OYw%3D%3D&sig=AOq0QJ8wRAIgTc5PFwG_YEKCapNc7GjFRYXy3pxXqGonDhdWoMpjXFwCIAqVP8RV0c5wmT9tIEOAL47eAS_BAs9faxkMk0p7SeHn", "width": 426, "ext": "mp4", "vcodec": "av01.0.00M.08", "acodec": "none", "vbr": 202.953, "downloader_options": {"http_chunk_size": 10485760}, "container": "mp4_dash", "format": "395 - 426x240 (240p)", "protocol": "https", "http_headers": {"User-Agent": "Mozilla/5.0 (Windows NT 10.0; Win64; x64) AppleWebKit/537.36 (KHTML, like Gecko) Chrome/73.0.3683.60 Safari/537.36", "Accept-Charset": "ISO-8859-1,utf-8;q=0.7,*;q=0.7", "Accept": "text/html,application/xhtml+xml,application/xml;q=0.9,*/*;q=0.8", "Accept-Encoding": "gzip, deflate", "Accept-Language": "en-us,en;q=0.5"}}, {"asr": null, "filesize": 3716422, "format_id": "134", "format_note": "360p", "fps": 24, "height": 360, "quality": 2, "tbr": 192.608, "url": "https://rr4---sn-0opoxu-ihv6.googlevideo.com/videoplayback?expire=1670740054&ei=9iOVY_j3KI2Ekgbqv4OoBA&ip=189.173.225.87&id=o-ADn5HJX_4ula4wHmV_FRxM8Tw5xvZmIBC4r7Sp-pgjAL&itag=134&aitags=133%2C134%2C135%2C136%2C137%2C160%2C242%2C243%2C244%2C247%2C248%2C278%2C394%2C395%2C396%2C397%2C398%2C399&source=youtube&requiressl=yes&mh=oY&mm=31%2C29&mn=sn-0opoxu-ihv6%2Csn-q4fzen7l&ms=au%2Crdu&mv=m&mvi=4&pl=24&gcr=mx&initcwndbps=793750&vprv=1&mime=video%2Fmp4&ns=FnthCqCD_zH0CFDuXEsFohEJ&gir=yes&clen=3716422&dur=154.362&lmt=1604864086235575&mt=1670718069&fvip=1&keepalive=yes&fexp=24001373%2C24007246&c=WEB&txp=5432434&n=UQts7oCbq-bc9e_WB&sparams=expire%2Cei%2Cip%2Cid%2Caitags%2Csource%2Crequiressl%2Cgcr%2Cvprv%2Cmime%2Cns%2Cgir%2Cclen%2Cdur%2Clmt&lsparams=mh%2Cmm%2Cmn%2Cms%2Cmv%2Cmvi%2Cpl%2Cinitcwndbps&lsig=AG3C_xAwRQIhAN7JtTsrARMybzaXdsuszsG4-MpPSh01sPXJlXTF5xGRAiAuWVBz9vvK9Z7HqWQK-u3-GYtmzb9gFgjYMovZALm6yA%3D%3D&sig=AOq0QJ8wRQIgAdzQA8w1fAVSK5nZRcTU26NhN911H2XAnPiaO_1Z6-wCIQCm9p4A0il5AG_VU2mOUNxODLcTcUecnVhBNqO4JpfQjg==", "width": 640, "ext": "mp4", "vcodec": "avc1.4d401e", "acodec": "none", "vbr": 192.608, "downloader_options": {"http_chunk_size": 10485760}, "container": "mp4_dash", "format": "134 - 640x360 (360p)", "protocol": "https", "http_headers": {"User-Agent": "Mozilla/5.0 (Windows NT 10.0; Win64; x64) AppleWebKit/537.36 (KHTML, like Gecko) Chrome/73.0.3683.60 Safari/537.36", "Accept-Charset": "ISO-8859-1,utf-8;q=0.7,*;q=0.7", "Accept": "text/html,application/xhtml+xml,application/xml;q=0.9,*/*;q=0.8", "Accept-Encoding": "gzip, deflate", "Accept-Language": "en-us,en;q=0.5"}}, {"asr": null, "filesize": 5555437, "format_id": "243", "format_note": "360p", "fps": 24, "height": 360, "quality": 2, "tbr": 287.917, "url": "https://rr4---sn-0opoxu-ihv6.googlevideo.com/videoplayback?expire=1670740054&ei=9iOVY_j3KI2Ekgbqv4OoBA&ip=189.173.225.87&id=o-ADn5HJX_4ula4wHmV_FRxM8Tw5xvZmIBC4r7Sp-pgjAL&itag=243&aitags=133%2C134%2C135%2C136%2C137%2C160%2C242%2C243%2C244%2C247%2C248%2C278%2C394%2C395%2C396%2C397%2C398%2C399&source=youtube&requiressl=yes&mh=oY&mm=31%2C29&mn=sn-0opoxu-ihv6%2Csn-q4fzen7l&ms=au%2Crdu&mv=m&mvi=4&pl=24&gcr=mx&initcwndbps=793750&vprv=1&mime=video%2Fwebm&ns=FnthCqCD_zH0CFDuXEsFohEJ&gir=yes&clen=5555437&dur=154.362&lmt=1604864120444919&mt=1670718069&fvip=1&keepalive=yes&fexp=24001373%2C24007246&c=WEB&txp=5432434&n=UQts7oCbq-bc9e_WB&sparams=expire%2Cei%2Cip%2Cid%2Caitags%2Csource%2Crequiressl%2Cgcr%2Cvprv%2Cmime%2Cns%2Cgir%2Cclen%2Cdur%2Clmt&lsparams=mh%2Cmm%2Cmn%2Cms%2Cmv%2Cmvi%2Cpl%2Cinitcwndbps&lsig=AG3C_xAwRgIhAMMjmqIhjZflOHQ5uTDx7BIkhr-1ZtA6ZNZiOxcXLmZQAiEA0O2DvK5kzteS9IBzGLMOHNrCsV_kkMpQGj5Mp9NnmOc%3D&sig=AOq0QJ8wRQIhAMcTmF850pULHsD0uEbDIXNQb5HOUkY3ryFnNveyebE2AiBKdT5zHRbw2yZBWTE3NMDeAB4zmZEFjqAlUGmOXOp2aQ==", "width": 640, "ext": "webm", "vcodec": "vp9", "acodec": "none", "vbr": 287.917, "downloader_options": {"http_chunk_size": 10485760}, "container": "webm_dash", "format": "243 - 640x360 (360p)", "protocol": "https", "http_headers": {"User-Agent": "Mozilla/5.0 (Windows NT 10.0; Win64; x64) AppleWebKit/537.36 (KHTML, like Gecko) Chrome/73.0.3683.60 Safari/537.36", "Accept-Charset": "ISO-8859-1,utf-8;q=0.7,*;q=0.7", "Accept": "text/html,application/xhtml+xml,application/xml;q=0.9,*/*;q=0.8", "Accept-Encoding": "gzip, deflate", "Accept-Language": "en-us,en;q=0.5"}}, {"asr": null, "filesize": 6373615, "format_id": "396", "format_note": "360p", "fps": 24, "height": 360, "quality": 2, "tbr": 330.32, "url": "https://rr4---sn-0opoxu-ihv6.googlevideo.com/videoplayback?expire=1670740054&ei=9iOVY_j3KI2Ekgbqv4OoBA&ip=189.173.225.87&id=o-ADn5HJX_4ula4wHmV_FRxM8Tw5xvZmIBC4r7Sp-pgjAL&itag=396&aitags=133%2C134%2C135%2C136%2C137%2C160%2C242%2C243%2C244%2C247%2C248%2C278%2C394%2C395%2C396%2C397%2C398%2C399&source=youtube&requiressl=yes&mh=oY&mm=31%2C29&mn=sn-0opoxu-ihv6%2Csn-q4fzen7l&ms=au%2Crdu&mv=m&mvi=4&pl=24&gcr=mx&initcwndbps=793750&vprv=1&mime=video%2Fmp4&ns=FnthCqCD_zH0CFDuXEsFohEJ&gir=yes&clen=6373615&dur=154.362&lmt=1622261456934521&mt=1670718069&fvip=1&keepalive=yes&fexp=24001373%2C24007246&c=WEB&txp=5436432&n=UQts7oCbq-bc9e_WB&sparams=expire%2Cei%2Cip%2Cid%2Caitags%2Csource%2Crequiressl%2Cgcr%2Cvprv%2Cmime%2Cns%2Cgir%2Cclen%2Cdur%2Clmt&lsparams=mh%2Cmm%2Cmn%2Cms%2Cmv%2Cmvi%2Cpl%2Cinitcwndbps&lsig=AG3C_xAwRAIgAuyedQlFnanJhcUbKRYKj05defmgMiwBgdhe68-SQeECIC_x9tE0qk4e6wq2YtsAMpiaTMNh0FIkzDLsG3B1zBi1&sig=AOq0QJ8wRgIhALmNXUZ6OwGouUmbfJ3O3f6K0KspMZQmZJwbXr-0Tdb7AiEAiAncPO4H-NJ2oo3Mde7KOmlw_veTPZMtXx0K-smzATw=", "width": 640, "ext": "mp4", "vcodec": "av01.0.01M.08", "acodec": "none", "vbr": 330.32, "downloader_options": {"http_chunk_size": 10485760}, "container": "mp4_dash", "format": "396 - 640x360 (360p)", "protocol": "https", "http_headers": {"User-Agent": "Mozilla/5.0 (Windows NT 10.0; Win64; x64) AppleWebKit/537.36 (KHTML, like Gecko) Chrome/73.0.3683.60 Safari/537.36", "Accept-Charset": "ISO-8859-1,utf-8;q=0.7,*;q=0.7", "Accept": "text/html,application/xhtml+xml,application/xml;q=0.9,*/*;q=0.8", "Accept-Encoding": "gzip, deflate", "Accept-Language": "en-us,en;q=0.5"}}, {"asr": null, "filesize": 6785107, "format_id": "135", "format_note": "480p", "fps": 24, "height": 480, "quality": 3, "tbr": 351.646, "url": "https://rr4---sn-0opoxu-ihv6.googlevideo.com/videoplayback?expire=1670740054&ei=9iOVY_j3KI2Ekgbqv4OoBA&ip=189.173.225.87&id=o-ADn5HJX_4ula4wHmV_FRxM8Tw5xvZmIBC4r7Sp-pgjAL&itag=135&aitags=133%2C134%2C135%2C136%2C137%2C160%2C242%2C243%2C244%2C247%2C248%2C278%2C394%2C395%2C396%2C397%2C398%2C399&source=youtube&requiressl=yes&mh=oY&mm=31%2C29&mn=sn-0opoxu-ihv6%2Csn-q4fzen7l&ms=au%2Crdu&mv=m&mvi=4&pl=24&gcr=mx&initcwndbps=793750&vprv=1&mime=video%2Fmp4&ns=FnthCqCD_zH0CFDuXEsFohEJ&gir=yes&clen=6785107&dur=154.362&lmt=1604864086263919&mt=1670718069&fvip=1&keepalive=yes&fexp=24001373%2C24007246&c=WEB&txp=5432434&n=UQts7oCbq-bc9e_WB&sparams=expire%2Cei%2Cip%2Cid%2Caitags%2Csource%2Crequiressl%2Cgcr%2Cvprv%2Cmime%2Cns%2Cgir%2Cclen%2Cdur%2Clmt&lsparams=mh%2Cmm%2Cmn%2Cms%2Cmv%2Cmvi%2Cpl%2Cinitcwndbps&lsig=AG3C_xAwRAIgUNO6cHusSZUfOga7hK44yPHwc1sy2v3tZEaDZmhHuGICIBb2EpvST3bFLsvg4b0nb6GzLJUe7gH9VHk9tWpuh1SH&sig=AOq0QJ8wRAIgclOPERlNLhGFYt7832nNpXKMWNtDst0fiq79n_5gPtMCIDbDXXItjQlIINKSiufx8qKaGcNtdEl--WJ1d-H6rwWQ", "width": 854, "ext": "mp4", "vcodec": "avc1.4d401e", "acodec": "none", "vbr": 351.646, "downloader_options": {"http_chunk_size": 10485760}, "container": "mp4_dash", "format": "135 - 854x480 (480p)", "protocol": "https", "http_headers": {"User-Agent": "Mozilla/5.0 (Windows NT 10.0; Win64; x64) AppleWebKit/537.36 (KHTML, like Gecko) Chrome/73.0.3683.60 Safari/537.36", "Accept-Charset": "ISO-8859-1,utf-8;q=0.7,*;q=0.7", "Accept": "text/html,application/xhtml+xml,application/xml;q=0.9,*/*;q=0.8", "Accept-Encoding": "gzip, deflate", "Accept-Language": "en-us,en;q=0.5"}}, {"asr": null, "filesize": 9295021, "format_id": "244", "format_note": "480p", "fps": 24, "height": 480, "quality": 3, "tbr": 481.725, "url": "https://rr4---sn-0opoxu-ihv6.googlevideo.com/videoplayback?expire=1670740054&ei=9iOVY_j3KI2Ekgbqv4OoBA&ip=189.173.225.87&id=o-ADn5HJX_4ula4wHmV_FRxM8Tw5xvZmIBC4r7Sp-pgjAL&itag=244&aitags=133%2C134%2C135%2C136%2C137%2C160%2C242%2C243%2C244%2C247%2C248%2C278%2C394%2C395%2C396%2C397%2C398%2C399&source=youtube&requiressl=yes&mh=oY&mm=31%2C29&mn=sn-0opoxu-ihv6%2Csn-q4fzen7l&ms=au%2Crdu&mv=m&mvi=4&pl=24&gcr=mx&initcwndbps=793750&vprv=1&mime=video%2Fwebm&ns=FnthCqCD_zH0CFDuXEsFohEJ&gir=yes&clen=9295021&dur=154.362&lmt=1604864122824067&mt=1670718069&fvip=1&keepalive=yes&fexp=24001373%2C24007246&c=WEB&txp=5432434&n=UQts7oCbq-bc9e_WB&sparams=expire%2Cei%2Cip%2Cid%2Caitags%2Csource%2Crequiressl%2Cgcr%2Cvprv%2Cmime%2Cns%2Cgir%2Cclen%2Cdur%2Clmt&lsparams=mh%2Cmm%2Cmn%2Cms%2Cmv%2Cmvi%2Cpl%2Cinitcwndbps&lsig=AG3C_xAwRgIhAM2lndrqlBCV04Azjg-1vtq7U-o5XSxnc8J-U0Kz1wuXAiEA-TuD_RLxznd9JVIMAWy4b25alQOKLGni7tkTFQPSUkU%3D&sig=AOq0QJ8wRQIgddAFZZ9wFVxJh9acjUht02UmEdbt3h7pXdaYCcnoy8sCIQCcuXruBRhdrUF8VCItPaNWsX8MkwKRYmyawQBBbP73Yw==", "width": 854, "ext": "webm", "vcodec": "vp9", "acodec": "none", "vbr": 481.725, "downloader_options": {"http_chunk_size": 10485760}, "container": "webm_dash", "format": "244 - 854x480 (480p)", "protocol": "https", "http_headers": {"User-Agent": "Mozilla/5.0 (Windows NT 10.0; Win64; x64) AppleWebKit/537.36 (KHTML, like Gecko) Chrome/73.0.3683.60 Safari/537.36", "Accept-Charset": "ISO-8859-1,utf-8;q=0.7,*;q=0.7", "Accept": "text/html,application/xhtml+xml,application/xml;q=0.9,*/*;q=0.8", "Accept-Encoding": "gzip, deflate", "Accept-Language": "en-us,en;q=0.5"}}, {"asr": null, "filesize": 11282587, "format_id": "397", "format_note": "480p", "fps": 24, "height": 480, "quality": 3, "tbr": 584.733, "url": "https://rr4---sn-0opoxu-ihv6.googlevideo.com/videoplayback?expire=1670740054&ei=9iOVY_j3KI2Ekgbqv4OoBA&ip=189.173.225.87&id=o-ADn5HJX_4ula4wHmV_FRxM8Tw5xvZmIBC4r7Sp-pgjAL&itag=397&aitags=133%2C134%2C135%2C136%2C137%2C160%2C242%2C243%2C244%2C247%2C248%2C278%2C394%2C395%2C396%2C397%2C398%2C399&source=youtube&requiressl=yes&mh=oY&mm=31%2C29&mn=sn-0opoxu-ihv6%2Csn-q4fzen7l&ms=au%2Crdu&mv=m&mvi=4&pl=24&gcr=mx&initcwndbps=793750&vprv=1&mime=video%2Fmp4&ns=FnthCqCD_zH0CFDuXEsFohEJ&gir=yes&clen=11282587&dur=154.362&lmt=1622261457015002&mt=1670718069&fvip=1&keepalive=yes&fexp=24001373%2C24007246&c=WEB&txp=5436432&n=UQts7oCbq-bc9e_WB&sparams=expire%2Cei%2Cip%2Cid%2Caitags%2Csource%2Crequiressl%2Cgcr%2Cvprv%2Cmime%2Cns%2Cgir%2Cclen%2Cdur%2Clmt&lsparams=mh%2Cmm%2Cmn%2Cms%2Cmv%2Cmvi%2Cpl%2Cinitcwndbps&lsig=AG3C_xAwRQIhAPooFp0xu2if9O7SW2St78gcJC6gBrwy3h3yvSkMgqzPAiAb6ELw1UGPr0IPAmISS1h2vN2VXMeF0KUdrBO8WVpV5w%3D%3D&sig=AOq0QJ8wRQIhAPjYryo4fIK7Wc7c3pbdH-ZzPlu2nT0bnALrPmBY7qjCAiBtYeNw0GOJAR_tipzvg9v_6n88F76udu_5pyDEP7zRdA==", "width": 854, "ext": "mp4", "vcodec": "av01.0.04M.08", "acodec": "none", "vbr": 584.733, "downloader_options": {"http_chunk_size": 10485760}, "container": "mp4_dash", "format": "397 - 854x480 (480p)", "protocol": "https", "http_headers": {"User-Agent": "Mozilla/5.0 (Windows NT 10.0; Win64; x64) AppleWebKit/537.36 (KHTML, like Gecko) Chrome/73.0.3683.60 Safari/537.36", "Accept-Charset": "ISO-8859-1,utf-8;q=0.7,*;q=0.7", "Accept": "text/html,application/xhtml+xml,application/xml;q=0.9,*/*;q=0.8", "Accept-Encoding": "gzip, deflate", "Accept-Language": "en-us,en;q=0.5"}}, {"asr": null, "filesize": 12097450, "format_id": "136", "format_note": "720p", "fps": 24, "height": 720, "quality": 4, "tbr": 626.965, "url": "https://rr4---sn-0opoxu-ihv6.googlevideo.com/videoplayback?expire=1670740054&ei=9iOVY_j3KI2Ekgbqv4OoBA&ip=189.173.225.87&id=o-ADn5HJX_4ula4wHmV_FRxM8Tw5xvZmIBC4r7Sp-pgjAL&itag=136&aitags=133%2C134%2C135%2C136%2C137%2C160%2C242%2C243%2C244%2C247%2C248%2C278%2C394%2C395%2C396%2C397%2C398%2C399&source=youtube&requiressl=yes&mh=oY&mm=31%2C29&mn=sn-0opoxu-ihv6%2Csn-q4fzen7l&ms=au%2Crdu&mv=m&mvi=4&pl=24&gcr=mx&initcwndbps=793750&vprv=1&mime=video%2Fmp4&ns=FnthCqCD_zH0CFDuXEsFohEJ&gir=yes&clen=12097450&dur=154.362&lmt=1604864086537763&mt=1670718069&fvip=1&keepalive=yes&fexp=24001373%2C24007246&c=WEB&txp=5432434&n=UQts7oCbq-bc9e_WB&sparams=expire%2Cei%2Cip%2Cid%2Caitags%2Csource%2Crequiressl%2Cgcr%2Cvprv%2Cmime%2Cns%2Cgir%2Cclen%2Cdur%2Clmt&lsparams=mh%2Cmm%2Cmn%2Cms%2Cmv%2Cmvi%2Cpl%2Cinitcwndbps&lsig=AG3C_xAwRQIhAJGXqnbeq3jUhToMwGIi1Its0s6b7ULi-yLFYiPLZ8UaAiApZdDD4siTn8eppfk9HuV5S6j4sgEiJ7UOf39pzsQlOg%3D%3D&sig=AOq0QJ8wRQIgDQjV6Ucdq0aWJiYkWIkQucO9Y2k3P22paM9BjaM-EO8CIQCXko_e2d2LvtQCPLhd7qyciZQF6ERkS1kTr7afoKbFJw==", "width": 1280, "ext": "mp4", "vcodec": "avc1.4d401f", "acodec": "none", "vbr": 626.965, "downloader_options": {"http_chunk_size": 10485760}, "container": "mp4_dash", "format": "136 - 1280x720 (720p)", "protocol": "https", "http_headers": {"User-Agent": "Mozilla/5.0 (Windows NT 10.0; Win64; x64) AppleWebKit/537.36 (KHTML, like Gecko) Chrome/73.0.3683.60 Safari/537.36", "Accept-Charset": "ISO-8859-1,utf-8;q=0.7,*;q=0.7", "Accept": "text/html,application/xhtml+xml,application/xml;q=0.9,*/*;q=0.8", "Accept-Encoding": "gzip, deflate", "Accept-Language": "en-us,en;q=0.5"}}, {"asr": null, "filesize": 18245174, "format_id": "247", "format_note": "720p", "fps": 24, "height": 720, "quality": 4, "tbr": 945.578, "url": "https://rr4---sn-0opoxu-ihv6.googlevideo.com/videoplayback?expire=1670740054&ei=9iOVY_j3KI2Ekgbqv4OoBA&ip=189.173.225.87&id=o-ADn5HJX_4ula4wHmV_FRxM8Tw5xvZmIBC4r7Sp-pgjAL&itag=247&aitags=133%2C134%2C135%2C136%2C137%2C160%2C242%2C243%2C244%2C247%2C248%2C278%2C394%2C395%2C396%2C397%2C398%2C399&source=youtube&requiressl=yes&mh=oY&mm=31%2C29&mn=sn-0opoxu-ihv6%2Csn-q4fzen7l&ms=au%2Crdu&mv=m&mvi=4&pl=24&gcr=mx&initcwndbps=793750&vprv=1&mime=video%2Fwebm&ns=FnthCqCD_zH0CFDuXEsFohEJ&gir=yes&clen=18245174&dur=154.362&lmt=1604864120727849&mt=1670718069&fvip=1&keepalive=yes&fexp=24001373%2C24007246&c=WEB&txp=5432434&n=UQts7oCbq-bc9e_WB&sparams=expire%2Cei%2Cip%2Cid%2Caitags%2Csource%2Crequiressl%2Cgcr%2Cvprv%2Cmime%2Cns%2Cgir%2Cclen%2Cdur%2Clmt&lsparams=mh%2Cmm%2Cmn%2Cms%2Cmv%2Cmvi%2Cpl%2Cinitcwndbps&lsig=AG3C_xAwRgIhAJtweinVlW1-YPV8_vK1yf5CRmimATFYmPXaezTBal3yAiEA_KKlIp3VWLkDW2R0BAWA2fKf3FHl2KiELpr7EOf8nQw%3D&sig=AOq0QJ8wRQIgc42eHLt5Sq71DNcXGgvBilzui2ESn9DLxPEG1SrDy4gCIQCiaMIWNadPnSLYCT04GJgy1q67abTL26t_vG0IvL0F5Q==", "width": 1280, "ext": "webm", "vcodec": "vp9", "acodec": "none", "vbr": 945.578, "downloader_options": {"http_chunk_size": 10485760}, "container": "webm_dash", "format": "247 - 1280x720 (720p)", "protocol": "https", "http_headers": {"User-Agent": "Mozilla/5.0 (Windows NT 10.0; Win64; x64) AppleWebKit/537.36 (KHTML, like Gecko) Chrome/73.0.3683.60 Safari/537.36", "Accept-Charset": "ISO-8859-1,utf-8;q=0.7,*;q=0.7", "Accept": "text/html,application/xhtml+xml,application/xml;q=0.9,*/*;q=0.8", "Accept-Encoding": "gzip, deflate", "Accept-Language": "en-us,en;q=0.5"}}, {"asr": null, "filesize": 21880618, "format_id": "398", "format_note": "720p", "fps": 24, "height": 720, "quality": 4, "tbr": 1133.989, "url": "https://rr4---sn-0opoxu-ihv6.googlevideo.com/videoplayback?expire=1670740054&ei=9iOVY_j3KI2Ekgbqv4OoBA&ip=189.173.225.87&id=o-ADn5HJX_4ula4wHmV_FRxM8Tw5xvZmIBC4r7Sp-pgjAL&itag=398&aitags=133%2C134%2C135%2C136%2C137%2C160%2C242%2C243%2C244%2C247%2C248%2C278%2C394%2C395%2C396%2C397%2C398%2C399&source=youtube&requiressl=yes&mh=oY&mm=31%2C29&mn=sn-0opoxu-ihv6%2Csn-q4fzen7l&ms=au%2Crdu&mv=m&mvi=4&pl=24&gcr=mx&initcwndbps=793750&vprv=1&mime=video%2Fmp4&ns=FnthCqCD_zH0CFDuXEsFohEJ&gir=yes&clen=21880618&dur=154.362&lmt=1622261458137851&mt=1670718069&fvip=1&keepalive=yes&fexp=24001373%2C24007246&c=WEB&txp=5436432&n=UQts7oCbq-bc9e_WB&sparams=expire%2Cei%2Cip%2Cid%2Caitags%2Csource%2Crequiressl%2Cgcr%2Cvprv%2Cmime%2Cns%2Cgir%2Cclen%2Cdur%2Clmt&lsparams=mh%2Cmm%2Cmn%2Cms%2Cmv%2Cmvi%2Cpl%2Cinitcwndbps&lsig=AG3C_xAwRgIhAPDt8-B0eaFuoiFwxy1YKzbCJCf5uinJ7BYo3izG2T02AiEAqK_5FZQFC4BiLv_Vi3jBin-5SRKkprwYSkWiWmc2W1c%3D&sig=AOq0QJ8wRQIhAIBc1NobC17lSHWcvBWRvziyvsEoZFId1AxpaHyLKAGfAiB8scr4HzhmjB0CtWYB9p46fEd7Pw_H9-VVU0Q3Z30rFg==", "width": 1280, "ext": "mp4", "vcodec": "av01.0.05M.08", "acodec": "none", "vbr": 1133.989, "downloader_options": {"http_chunk_size": 10485760}, "container": "mp4_dash", "format": "398 - 1280x720 (720p)", "protocol": "https", "http_headers": {"User-Agent": "Mozilla/5.0 (Windows NT 10.0; Win64; x64) AppleWebKit/537.36 (KHTML, like Gecko) Chrome/73.0.3683.60 Safari/537.36", "Accept-Charset": "ISO-8859-1,utf-8;q=0.7,*;q=0.7", "Accept": "text/html,application/xhtml+xml,application/xml;q=0.9,*/*;q=0.8", "Accept-Encoding": "gzip, deflate", "Accept-Language": "en-us,en;q=0.5"}}, {"asr": null, "filesize": 37364706, "format_id": "399", "format_note": "1080p", "fps": 24, "height": 1080, "quality": 5, "tbr": 1936.471, "url": "https://rr4---sn-0opoxu-ihv6.googlevideo.com/videoplayback?expire=1670740054&ei=9iOVY_j3KI2Ekgbqv4OoBA&ip=189.173.225.87&id=o-ADn5HJX_4ula4wHmV_FRxM8Tw5xvZmIBC4r7Sp-pgjAL&itag=399&aitags=133%2C134%2C135%2C136%2C137%2C160%2C242%2C243%2C244%2C247%2C248%2C278%2C394%2C395%2C396%2C397%2C398%2C399&source=youtube&requiressl=yes&mh=oY&mm=31%2C29&mn=sn-0opoxu-ihv6%2Csn-q4fzen7l&ms=au%2Crdu&mv=m&mvi=4&pl=24&gcr=mx&initcwndbps=793750&vprv=1&mime=video%2Fmp4&ns=FnthCqCD_zH0CFDuXEsFohEJ&gir=yes&clen=37364706&dur=154.362&lmt=1622261460335114&mt=1670718069&fvip=1&keepalive=yes&fexp=24001373%2C24007246&c=WEB&txp=5436432&n=UQts7oCbq-bc9e_WB&sparams=expire%2Cei%2Cip%2Cid%2Caitags%2Csource%2Crequiressl%2Cgcr%2Cvprv%2Cmime%2Cns%2Cgir%2Cclen%2Cdur%2Clmt&lsparams=mh%2Cmm%2Cmn%2Cms%2Cmv%2Cmvi%2Cpl%2Cinitcwndbps&lsig=AG3C_xAwRAIgc2Iq2zRuR4MFOBjcOxmx7dIa-g4MvYDmrQvfsxv0QigCIAzP_gn0td7627odAgYos_3LMrQEGvqSlX5TsJRHKGlF&sig=AOq0QJ8wRQIhAN2L2dJT_jQx19EbkFyRHd2TH8q9PHsc73osL1POYqEfAiBcSiG7qyMwmsnQkInHwB_YPrNpLuqk6Ft1iFwgoFV_Gw==", "width": 1920, "ext": "mp4", "vcodec": "av01.0.08M.08", "acodec": "none", "vbr": 1936.471, "downloader_options": {"http_chunk_size": 10485760}, "container": "mp4_dash", "format": "399 - 1920x1080 (1080p)", "protocol": "https", "http_headers": {"User-Agent": "Mozilla/5.0 (Windows NT 10.0; Win64; x64) AppleWebKit/537.36 (KHTML, like Gecko) Chrome/73.0.3683.60 Safari/537.36", "Accept-Charset": "ISO-8859-1,utf-8;q=0.7,*;q=0.7", "Accept": "text/html,application/xhtml+xml,application/xml;q=0.9,*/*;q=0.8", "Accept-Encoding": "gzip, deflate", "Accept-Language": "en-us,en;q=0.5"}}, {"asr": null, "filesize": 39191266, "format_id": "248", "format_note": "1080p", "fps": 24, "height": 1080, "quality": 5, "tbr": 2031.135, "url": "https://rr4---sn-0opoxu-ihv6.googlevideo.com/videoplayback?expire=1670740054&ei=9iOVY_j3KI2Ekgbqv4OoBA&ip=189.173.225.87&id=o-ADn5HJX_4ula4wHmV_FRxM8Tw5xvZmIBC4r7Sp-pgjAL&itag=248&aitags=133%2C134%2C135%2C136%2C137%2C160%2C242%2C243%2C244%2C247%2C248%2C278%2C394%2C395%2C396%2C397%2C398%2C399&source=youtube&requiressl=yes&mh=oY&mm=31%2C29&mn=sn-0opoxu-ihv6%2Csn-q4fzen7l&ms=au%2Crdu&mv=m&mvi=4&pl=24&gcr=mx&initcwndbps=793750&vprv=1&mime=video%2Fwebm&ns=FnthCqCD_zH0CFDuXEsFohEJ&gir=yes&clen=39191266&dur=154.362&lmt=1604864108766514&mt=1670718069&fvip=1&keepalive=yes&fexp=24001373%2C24007246&c=WEB&txp=5432434&n=UQts7oCbq-bc9e_WB&sparams=expire%2Cei%2Cip%2Cid%2Caitags%2Csource%2Crequiressl%2Cgcr%2Cvprv%2Cmime%2Cns%2Cgir%2Cclen%2Cdur%2Clmt&lsparams=mh%2Cmm%2Cmn%2Cms%2Cmv%2Cmvi%2Cpl%2Cinitcwndbps&lsig=AG3C_xAwRAIgUg72YXmZ4PnfQ5slmtpBIqdqVmXnhizsppWRgf7391YCIHs7D5fmkR8h7CE_RunUNMRD2ienHAP9wZVhZ4InoS10&sig=AOq0QJ8wRQIgTeYiNcG7ZtNvkgA4QEjlgLqcZfv2QkCQw1kZgLIqWb0CIQD6I9IlN6KILwAMV6evXdvS_Hc-Ze2Vd8OFjMMAK2kb-g==", "width": 1920, "ext": "webm", "vcodec": "vp9", "acodec": "none", "vbr": 2031.135, "downloader_options": {"http_chunk_size": 10485760}, "container": "webm_dash", "format": "248 - 1920x1080 (1080p)", "protocol": "https", "http_headers": {"User-Agent": "Mozilla/5.0 (Windows NT 10.0; Win64; x64) AppleWebKit/537.36 (KHTML, like Gecko) Chrome/73.0.3683.60 Safari/537.36", "Accept-Charset": "ISO-8859-1,utf-8;q=0.7,*;q=0.7", "Accept": "text/html,application/xhtml+xml,application/xml;q=0.9,*/*;q=0.8", "Accept-Encoding": "gzip, deflate", "Accept-Language": "en-us,en;q=0.5"}}, {"asr": null, "filesize": 42867521, "format_id": "137", "format_note": "1080p", "fps": 24, "height": 1080, "quality": 5, "tbr": 2221.661, "url": "https://rr4---sn-0opoxu-ihv6.googlevideo.com/videoplayback?expire=1670740054&ei=9iOVY_j3KI2Ekgbqv4OoBA&ip=189.173.225.87&id=o-ADn5HJX_4ula4wHmV_FRxM8Tw5xvZmIBC4r7Sp-pgjAL&itag=137&aitags=133%2C134%2C135%2C136%2C137%2C160%2C242%2C243%2C244%2C247%2C248%2C278%2C394%2C395%2C396%2C397%2C398%2C399&source=youtube&requiressl=yes&mh=oY&mm=31%2C29&mn=sn-0opoxu-ihv6%2Csn-q4fzen7l&ms=au%2Crdu&mv=m&mvi=4&pl=24&gcr=mx&initcwndbps=793750&vprv=1&mime=video%2Fmp4&ns=FnthCqCD_zH0CFDuXEsFohEJ&gir=yes&clen=42867521&dur=154.362&lmt=1604864582645217&mt=1670718069&fvip=1&keepalive=yes&fexp=24001373%2C24007246&c=WEB&txp=5432434&n=UQts7oCbq-bc9e_WB&sparams=expire%2Cei%2Cip%2Cid%2Caitags%2Csource%2Crequiressl%2Cgcr%2Cvprv%2Cmime%2Cns%2Cgir%2Cclen%2Cdur%2Clmt&lsparams=mh%2Cmm%2Cmn%2Cms%2Cmv%2Cmvi%2Cpl%2Cinitcwndbps&lsig=AG3C_xAwRAIgdziTs_7rWo5R-OI7B9FUqbZETmTKYu5OKGqP6NMDswUCIBAbq9FXNrj-Nj1lSKQ943gJwLjInhUVb9IXw12qIpa_&sig=AOq0QJ8wRAIgNSeJnKfPSBX5HSPtBGvZ8BNwIdlyOJCie-5FA15124kCIDdXPQcp6JuIucIfajb1-rnmocrGQlsLQtfCGYWSs3xg", "width": 1920, "ext": "mp4", "vcodec": "avc1.640028", "acodec": "none", "vbr": 2221.661, "downloader_options": {"http_chunk_size": 10485760}, "container": "mp4_dash", "format": "137 - 1920x1080 (1080p)", "protocol": "https", "http_headers": {"User-Agent": "Mozilla/5.0 (Windows NT 10.0; Win64; x64) AppleWebKit/537.36 (KHTML, like Gecko) Chrome/73.0.3683.60 Safari/537.36", "Accept-Charset": "ISO-8859-1,utf-8;q=0.7,*;q=0.7", "Accept": "text/html,application/xhtml+xml,application/xml;q=0.9,*/*;q=0.8", "Accept-Encoding": "gzip, deflate", "Accept-Language": "en-us,en;q=0.5"}}, {"asr": 44100, "filesize": null, "format_id": "18", "format_note": "360p", "fps": 24, "height": 360, "quality": 2, "tbr": 321.677, "url": "https://rr4---sn-0opoxu-ihv6.googlevideo.com/videoplayback?expire=1670740054&ei=9iOVY_j3KI2Ekgbqv4OoBA&ip=189.173.225.87&id=o-ADn5HJX_4ula4wHmV_FRxM8Tw5xvZmIBC4r7Sp-pgjAL&itag=18&source=youtube&requiressl=yes&mh=oY&mm=31%2C29&mn=sn-0opoxu-ihv6%2Csn-q4fzen7l&ms=au%2Crdu&mv=m&mvi=4&pl=24&gcr=mx&initcwndbps=793750&vprv=1&mime=video%2Fmp4&ns=mF1jfyNcuYegWt69aJ5P4CYJ&cnr=14&ratebypass=yes&dur=154.412&lmt=1665135569442089&mt=1670718069&fvip=1&fexp=24001373%2C24007246&c=WEB&txp=5438434&n=kgEOmUBsaDVAheX9D&sparams=expire%2Cei%2Cip%2Cid%2Citag%2Csource%2Crequiressl%2Cgcr%2Cvprv%2Cmime%2Cns%2Ccnr%2Cratebypass%2Cdur%2Clmt&lsparams=mh%2Cmm%2Cmn%2Cms%2Cmv%2Cmvi%2Cpl%2Cinitcwndbps&lsig=AG3C_xAwRQIhAPNrH9SGtUI3OOpkHZXO9tU2xkpHMJ-B_SN6YFmKd4NLAiBJjA50CYeivQbaTzIb7MOh91xO_Iu-JcMNaucbgckLHg%3D%3D&sig=AOq0QJ8wRQIhAJzKT0HE5vM2HpwKR3jODb0YEIfjolsCB158gcoiWSMVAiBLpF5V2eOUMGjFOUowGFNR5K5d-Rm_nUAiCWxsUWI3ug==", "width": 640, "ext": "mp4", "vcodec": "avc1.42001E", "acodec": "mp4a.40.2", "format": "18 - 640x360 (360p)", "protocol": "https", "http_headers": {"User-Agent": "Mozilla/5.0 (Windows NT 10.0; Win64; x64) AppleWebKit/537.36 (KHTML, like Gecko) Chrome/73.0.3683.60 Safari/537.36", "Accept-Charset": "ISO-8859-1,utf-8;q=0.7,*;q=0.7", "Accept": "text/html,application/xhtml+xml,application/xml;q=0.9,*/*;q=0.8", "Accept-Encoding": "gzip, deflate", "Accept-Language": "en-us,en;q=0.5"}}], "thumbnails": [{"height": 94, "url": "https://i.ytimg.com/vi/D6Aw3ZnqQrY/hqdefault.jpg?sqp=-oaymwEbCKgBEF5IVfKriqkDDggBFQAAiEIYAXABwAEG&rs=AOn4CLASJKFM5iAUedqvXafsOwMRjhOwfQ", "width": 168, "resolution": "168x94", "id": "0"}, {"height": 110, "url": "https://i.ytimg.com/vi/D6Aw3ZnqQrY/hqdefault.jpg?sqp=-oaymwEbCMQBEG5IVfKriqkDDggBFQAAiEIYAXABwAEG&rs=AOn4CLBH7XjIhx3vldo8MiqOLvvqkCf1SQ", "width": 196, "resolution": "196x110", "id": "1"}, {"height": 138, "url": "https://i.ytimg.com/vi/D6Aw3ZnqQrY/hqdefault.jpg?sqp=-oaymwEcCPYBEIoBSFXyq4qpAw4IARUAAIhCGAFwAcABBg==&rs=AOn4CLBAEq9jQ9UlSnEMzs-5rTGV2uurDw", "width": 246, "resolution": "246x138", "id": "2"}, {"height": 188, "url": "https://i.ytimg.com/vi/D6Aw3ZnqQrY/hqdefault.jpg?sqp=-oaymwEcCNACELwBSFXyq4qpAw4IARUAAIhCGAFwAcABBg==&rs=AOn4CLDKR8cgSxsRJxfaKh6nH1ODNACzEw", "width": 336, "resolution": "336x188", "id": "3"}, {"height": 1080, "url": "https://i.ytimg.com/vi/D6Aw3ZnqQrY/maxresdefault.jpg", "width": 1920, "resolution": "1920x1080", "id": "4"}], "description": "\"Only The Lonely\" by Roy Orbison from Black & White Night 30\nListen to Roy Orbison: https://RoyOrbison.lnk.to/listenYD\n\nSubscribe to the official Roy Orbison YouTube channel: https://RoyOrbison.lnk.to/subscribeYD\n\nFollow Roy Orbison: \nFacebook: https://RoyOrbison.lnk.to/followFI\nInstagram: https://RoyOrbison.lnk.to/followII\nTwitter: https://RoyOrbison.lnk.to/followTI\nWebsite: https://RoyOrbison.lnk.to/followWI\nSpotify: https://RoyOrbison.lnk.to/followSI\nYouTube: https://RoyOrbison.lnk.to/subscribeYD\n\nChorus: \nOnly the lonely (dum-dumb-dummy doo-wah)\nKnow the heartaches I've been through (ooh yay, yay, yay, yeah)\nOnly the lonely (dum-dumb-dummy doo-wah)\nKnow I cry and cry for you (dum-dumb-dummy doo-wah)\n\n#RoyOrbison #OnlytheLonely #BlackandWhiteNight30", "upload_date": "20190912", "uploader": "RoyOrbisonVEVO", "uploader_id": "RoyOrbisonVEVO", "uploader_url": "http://www.youtube.com/user/RoyOrbisonVEVO", "channel_id": "UCbyNoL1S5KkJ7PuwxoGTCtQ", "channel_url": "https://www.youtube.com/channel/UCbyNoL1S5KkJ7PuwxoGTCtQ", "duration": 154, "view_count": 7659688, "average_rating": null, "age_limit": 0, "webpage_url": "https://www.youtube.com/watch?v=D6Aw3ZnqQrY", "categories": ["Music"], "tags": ["Roy orbison", "Only the Lonely roy orbison", "roy orbison Only the Lonely", "black and white night 30", "black white night 30", "roy orbison black and white night", "roy orbison concert", "roy orbison live show", "full performance roy orbison", "black and white night full show", "Elvis Presley", "TCB Band", "Elvis Presley TCB Band", "roy orbison facebook live", "roy orbison birthday", "roy orbison facebook watch party", "pretty woman", "you got it", "only the lonely", "crying"], "is_live": null, "channel": "Roy Orbison", "extractor": "youtube", "webpage_url_basename": "watch", "extractor_key": "Youtube", "playlist": null, "playlist_index": null, "thumbnail": "https://i.ytimg.com/vi/D6Aw3ZnqQrY/maxresdefault.jpg", "display_id": "D6Aw3ZnqQrY", "asr": 44100, "filesize": null, "format_id": "18", "format_note": "360p", "fps": 24, "height": 360, "quality": 2, "tbr": 321.677, "url": "https://rr4---sn-0opoxu-ihv6.googlevideo.com/videoplayback?expire=1670740054&ei=9iOVY_j3KI2Ekgbqv4OoBA&ip=189.173.225.87&id=o-ADn5HJX_4ula4wHmV_FRxM8Tw5xvZmIBC4r7Sp-pgjAL&itag=18&source=youtube&requiressl=yes&mh=oY&mm=31%2C29&mn=sn-0opoxu-ihv6%2Csn-q4fzen7l&ms=au%2Crdu&mv=m&mvi=4&pl=24&gcr=mx&initcwndbps=793750&vprv=1&mime=video%2Fmp4&ns=mF1jfyNcuYegWt69aJ5P4CYJ&cnr=14&ratebypass=yes&dur=154.412&lmt=1665135569442089&mt=1670718069&fvip=1&fexp=24001373%2C24007246&c=WEB&txp=5438434&n=kgEOmUBsaDVAheX9D&sparams=expire%2Cei%2Cip%2Cid%2Citag%2Csource%2Crequiressl%2Cgcr%2Cvprv%2Cmime%2Cns%2Ccnr%2Cratebypass%2Cdur%2Clmt&lsparams=mh%2Cmm%2Cmn%2Cms%2Cmv%2Cmvi%2Cpl%2Cinitcwndbps&lsig=AG3C_xAwRQIhAPNrH9SGtUI3OOpkHZXO9tU2xkpHMJ-B_SN6YFmKd4NLAiBJjA50CYeivQbaTzIb7MOh91xO_Iu-JcMNaucbgckLHg%3D%3D&sig=AOq0QJ8wRQIhAJzKT0HE5vM2HpwKR3jODb0YEIfjolsCB158gcoiWSMVAiBLpF5V2eOUMGjFOUowGFNR5K5d-Rm_nUAiCWxsUWI3ug==", "width": 640, "ext": "mp4", "vcodec": "avc1.42001E", "acodec": "mp4a.40.2", "format": "18 - 640x360 (360p)", "protocol": "https", "http_headers": {"User-Agent": "Mozilla/5.0 (Windows NT 10.0; Win64; x64) AppleWebKit/537.36 (KHTML, like Gecko) Chrome/73.0.3683.60 Safari/537.36", "Accept-Charset": "ISO-8859-1,utf-8;q=0.7,*;q=0.7", "Accept": "text/html,application/xhtml+xml,application/xml;q=0.9,*/*;q=0.8", "Accept-Encoding": "gzip, deflate", "Accept-Language": "en-us,en;q=0.5"}, "fulltitle": "Roy Orbison - Only the Lonely (Black & White Night 30)", "_filename": "Roy Orbison - Only the Lonely (Black & White Night 30)-D6Aw3ZnqQrY.mp4"}